LICENSE
README.rst
jservicepy.py
jservicepy-1.0.dist-info/LICENSE
jservicepy-1.0.dist-info/WHEEL
jservicepy-1.0.dist-info/METADATA
jservicepy-1.0.dist-info/RECORD
